dual_port_ram.v
module dual_port_ram(
  input [7:0] data_a, data_b, 
  input [5:0] addr_a, addr_b, 
  input we_a, we_b,           
  input clk,                  
  output reg [7:0] q_a, q_b   
);
reg [7:0] ram [63:0]; 
 always @ (posedge clk) begin
    if (we_a) begin
      ram[addr_a] <= data_a;
    end else begin
      q_a <= ram[addr_a]; 
    end
  end
 always @ (posedge clk) begin
    if (we_b) begin
      ram[addr_b] <= data_b;
    end else begin
      q_b <= ram[addr_b]; 
    end
  end 
endmodule

dual_port_ram_tb.v
`timescale 1ns / 1ps

module dual_port_ram_tb;
  reg [7:0] data_a, data_b;
  reg [5:0] addr_a, addr_b;
  reg we_a, we_b;
  reg clk;
  wire [7:0] q_a, q_b;
  dual_port_ram dpr1 (
    .data_a(data_a),
    .data_b(data_b),
    .addr_a(addr_a),
    .addr_b(addr_b),
    .we_a(we_a),
    .we_b(we_b),
    .clk(clk),
    .q_a(q_a),
    .q_b(q_b)
  );
  initial begin
    clk = 1'b0;
    forever #5 clk = ~clk;
  end
  initial begin
    $dumpfile("dump.vcd");
    $dumpvars(0, dual_port_ram_tb); 
  end
  initial begin
    $monitor("Time=%0t | we_a=%b addr_a=%2d data_a=%3d q_a=%3d | we_b=%b addr_b=%2d data_b=%3d q_b=%3d", 
             $time, we_a, addr_a, data_a, q_a, we_b, addr_b, data_b, q_b);
    we_a = 1'b0;    we_b = 1'b0;
    addr_a = 6'd0;  addr_b = 6'd0;
    data_a = 8'd0;  data_b = 8'd0;
    #10; // Wait for initial stable state
    data_a = 8'd33; addr_a = 6'd1; we_a = 1'b1;
    data_b = 8'd44; addr_b = 6'd2; we_b = 1'b1;
    #10;
    we_a = 1'b0; we_b = 1'b0;
    #10;           

    data_a = 8'd60; addr_a = 6'd4; we_a = 1'b1;
    #10;
      
    data_a = 8'd62; addr_a = 6'd5; we_a = 1'b1;
    #10;
       
    we_a = 1'b0;   // Turn off writing on Port A
    addr_b = 6'd4; we_b = 1'b0; // Read address 4 from Port B
    #10; 
    
    addr_b = 6'd5; we_b = 1'b0; // Read address 5 from Port B
    #10; 
    
    // --- TEST 3: Write on Port B, Read on Port A ---
    data_b = 8'd70; addr_b = 6'd8; we_b = 1'b1;
    #10;
      
    data_b = 8'd72; addr_b = 6'd9; we_b = 1'b1;
    #10;
      
    we_b = 1'b0;   // Turn off writing on Port B
    addr_a = 6'd8; we_a = 1'b0;  // Read address 8 from Port A
    #10;
     
    addr_a = 6'd9; we_a = 1'b0;  // Read address 9 from Port A
    #10; 
        
    data_b = 8'd45; addr_b = 6'd15; we_b = 1'b1;
    #10; 
     
    we_b = 1'b0;
    data_a = 8'd15; addr_a = 6'd15; we_a = 1'b1;
    #10; 
     
    we_a = 1'b0; we_b = 1'b0;
    addr_a = 6'd15;
    addr_b = 6'd15;
    #10; 
      
    $finish;    
  end 
  
endmodule

dual_port_ram.vcd
$date
	Fri Jun 26 12:58:28 2026
$end
$version
	Icarus Verilog
$end
$timescale
	1ps
$end
$scope module dual_port_ram_tb $end
$var wire 8 ! q_b [7:0] $end
$var wire 8 " q_a [7:0] $end
$var reg 6 # addr_a [5:0] $end
$var reg 6 $ addr_b [5:0] $end
$var reg 1 % clk $end
$var reg 8 & data_a [7:0] $end
$var reg 8 ' data_b [7:0] $end
$var reg 1 ( we_a $end
$var reg 1 ) we_b $end
$scope module dpr1 $end
$var wire 6 * addr_a [5:0] $end
$var wire 6 + addr_b [5:0] $end
$var wire 1 % clk $end
$var wire 8 , data_a [7:0] $end
$var wire 8 - data_b [7:0] $end
$var wire 1 ( we_a $end
$var wire 1 ) we_b $end
$var reg 8 . q_a [7:0] $end
$var reg 8 / q_b [7:0] $end
$upscope $end
$upscope $end
$enddefinitions $end
#0
$dumpvars
bx /
bx .
b0 -
b0 ,
b0 +
b0 *
0)
0(
b0 '
b0 &
0%
b0 $
b0 #
bx "
bx !
$end
#5000
1%
#10000
0%
1)
b10 $
b10 +
b101100 '
b101100 -
1(
b1 #
b1 *
b100001 &
b100001 ,
#15000
1%
#20000
0%
0)
0(
#25000
b100001 "
b100001 .
b101100 !
b101100 /
1%
#30000
0%
1(
b100 #
b100 *
b111100 &
b111100 ,
#35000
1%
#40000
0%
b101 #
b101 *
b111110 &
b111110 ,
#45000
1%
#50000
0%
b100 $
b100 +
0(
#55000
b111100 !
b111100 /
b111110 "
b111110 .
1%
#60000
0%
b101 $
b101 +
#65000
b111110 !
b111110 /
1%
#70000
0%
1)
b1000 $
b1000 +
b1000110 '
b1000110 -
#75000
1%
#80000
0%
b1001 $
b1001 +
b1001000 '
b1001000 -
#85000
1%
#90000
0%
b1000 #
b1000 *
0)
#95000
b1001000 !
b1001000 /
b1000110 "
b1000110 .
1%
#100000
0%
b1001 #
b1001 *
#105000
b1001000 "
b1001000 .
1%
#110000
0%
1)
b1111 $
b1111 +
b101101 '
b101101 -
#115000
1%
#120000
0%
1(
b1111 #
b1111 *
b1111 &
b1111 ,
0)
#125000
b101101 !
b101101 /
1%
#130000
0%
0(
#135000
b1111 !
b1111 /
b1111 "
b1111 .
1%
